cpakage/__init__.py
cpakage/main.py
cpakage-0.0.1.dist-info/METADATA
cpakage-0.0.1.dist-info/WHEEL
cpakage-0.0.1.dist-info/entry_points.txt
cpakage-0.0.1.dist-info/top_level.txt
cpakage-0.0.1.dist-info/RECORD
