Metadata-Version: 2.1
Name: cpakage
Version: 0.0.1
Summary: A package management tool for C++ libraries
Home-page: https://cpakage.example.com
Author: Kamran Najafi
Author-email: 
Classifier: Programming Language :: Python :: 3
Classifier: License :: OSI Approved :: MIT License
Classifier: Operating System :: OS Independent
Requires-Python: >=3.6
Requires-Dist: requests
